{"name":"CIVICS.com","tagline":"","body":"The New CIVICS.com Site Is On The Way....\r\n\r\n------\r\n# Bio\r\n\r\nDazza” Greenwood heads CIVICS.com, a boutique provider of professional consultancy services. Engagements are tailored to purpose and leverage innovative solutions for digital identity, data strategy and technology policy. Dazza is a Lecturer and Scientist at the MIT Media Lab, focused on public policy, information technology and innovation with emphasis on big data, identity federation, personal data sharing and system design research and development. Dazza consults to fortune 100 companies, including the insurance industry and financial services sector, architecting the creation of trust frameworks. As an attorney, Dazza served as both general and special counsel for technology law, representing corporations and governments and as intellectual property litigation expert.\r\n\r\n\r\nFederally, Dazza has testified several times on eCommerce before the US House and US Senate and other legislatures and has consulted to NASA as an Online Identity expert, GSA as a multilateral rules drafting expert, Homeland Security as a multistate federated governance expert, the UK Cabinet Office GDS facilitating and authoring identity federation rules and many other public and private sector organizations.\r\n\r\n\r\nDazza was elected as Vice Chair of the Identity Ecosystem Steering Group’s Plenary, which is developing a framework for federated identity and privacy at the international level, implementing NSTIC. Dazza Chairs the Forum on Law of Identity and Personal Data of the ID Commons. Dazza chaired the eContracts Committee of OASIS/LegalXML, which approved and published the Technical Committee Specification for eContracts in 2007.\r\n\r\n\r\nDazza served as an arbitrator under the Internet Corporation for Assigned Names and Numbers (ICANN), where he arbitrated Internet domain name and trademark disputes. Mr. Greenwood has successfully mediated several domain name and other disputes. Mr Greenwood created legal processes for online mediation used by eBay and other online dispute resolution providers, crafted the first crowd-sourced dispute resolution process and vice chaired of the OASIS Online Dispute Resolution technical specifications committee.\r\n\r\n# Areas of Focus\r\n\r\n## /innovation\r\nENTREPRENEURSHIP & INNOVATION\r\n* Catalyzing Entrepreneurship & Innovation via Academic Affiliations\r\n\r\n## /systems\r\nSYSTEMS DESIGN & ARCHITECTURE\r\n* Deploying Breakthrough Systems Design & Architecture via Industry Partnerships\r\n\r\n## /contribution\r\nPUBLIC SERVICE & CONTRIBUTION\r\n* Reforming Policy and Legislation vis Public Service & Civic Contribution","google":"","note":"Don't delete this file! It's used internally to help with page regeneration."}